odoo9_addon_mrp_bom_current_stock-9.0.1.0.0-py2.7-nspkg.pth
odoo9_addon_mrp_bom_current_stock-9.0.1.0.0.dist-info/DESCRIPTION.rst
odoo9_addon_mrp_bom_current_stock-9.0.1.0.0.dist-info/METADATA
odoo9_addon_mrp_bom_current_stock-9.0.1.0.0.dist-info/RECORD
odoo9_addon_mrp_bom_current_stock-9.0.1.0.0.dist-info/WHEEL
odoo9_addon_mrp_bom_current_stock-9.0.1.0.0.dist-info/metadata.json
odoo9_addon_mrp_bom_current_stock-9.0.1.0.0.dist-info/namespace_packages.txt
odoo9_addon_mrp_bom_current_stock-9.0.1.0.0.dist-info/top_level.txt
odoo_addons/mrp_bom_current_stock/README.rst
odoo_addons/mrp_bom_current_stock/__init__.py
odoo_addons/mrp_bom_current_stock/__openerp__.py
odoo_addons/mrp_bom_current_stock/reports/report_mrpcurrentstock.xml
odoo_addons/mrp_bom_current_stock/static/description/icon.png
odoo_addons/mrp_bom_current_stock/wizard/__init__.py
odoo_addons/mrp_bom_current_stock/wizard/bom_route_current_stock.py
odoo_addons/mrp_bom_current_stock/wizard/bom_route_current_stock_view.xml
